pharindoko/cdk_internal_gateway/__init__.py
pharindoko/cdk_internal_gateway/py.typed
pharindoko/cdk_internal_gateway/_jsii/__init__.py
pharindoko/cdk_internal_gateway/_jsii/cdk-internal-gateway@1.5.1.jsii.tgz
pharindoko_cdk_internal_gateway-1.5.1.dist-info/LICENSE
pharindoko_cdk_internal_gateway-1.5.1.dist-info/METADATA
pharindoko_cdk_internal_gateway-1.5.1.dist-info/WHEEL
pharindoko_cdk_internal_gateway-1.5.1.dist-info/top_level.txt
pharindoko_cdk_internal_gateway-1.5.1.dist-info/RECORD
