Metadata-Version: 2.1
Name: pharindoko.cdk-internal-gateway
Version: 1.5.1
Summary: CDK construct to create to create internal serverless applications.
Home-page: https://github.com/pharindoko/cdk-internal-gateway.git
Author: Florian Fuß
License: Apache-2.0
Project-URL: Source, https://github.com/pharindoko/cdk-internal-gateway.git
Classifier: Intended Audience :: Developers
Classifier: Operating System :: OS Independent
Classifier: Programming Language :: JavaScript
Classifier: Programming Language :: Python :: 3 :: Only
Classifier: Programming Language :: Python :: 3.9
Classifier: Programming Language :: Python :: 3.10
Classifier: Programming Language :: Python :: 3.11
Classifier: Typing :: Typed
Classifier: Development Status :: 5 - Production/Stable
Classifier: License :: OSI Approved
Requires-Python: ~=3.9
License-File: LICENSE
Requires-Dist: aws-cdk-lib<3.0.0,>=2.78.0
Requires-Dist: constructs<11.0.0,>=10.0.5
Requires-Dist: jsii<2.0.0,>=1.111.0
Requires-Dist: publication>=0.0.3
Requires-Dist: typeguard<4.3.0,>=2.13.3
